logformatter
