Metadata-Version: 2.1
Name: logformatter
Version: 0.4
Summary: A very simple log formatter for the logging module that can be used as is
Home-page: https://github.com/JulienBrn/LogFormatter
Download-URL: https://github.com/JulienBrn/LogFormatter.git
Author: Julien Braine
Author-email: julienbraine@yahoo.fr
License: MIT
Keywords: python,logging
License-File: LICENSE.txt
